MANIFEST.in
README.txt
VERSION.txt
ez_setup.py
functional-testing.cfg
setup.cfg
setup.py
docs/Makefile
docs/source/News.rst
docs/source/Participate.rst
docs/source/conf.py
docs/source/index.rst
docs/source/Manual/GettingStarted.rst
docs/source/Manual/InnerWorkings.rst
docs/source/Manual/ManagingSources.rst
docs/source/Manual/index.rst
docs/source/Manual/Plugins/index.rst
docs/source/Manual/Predicates/Builtin.rst
docs/source/Manual/Predicates/Evaluating.rst
docs/source/Manual/Predicates/Writing.rst
docs/source/Manual/Predicates/index.rst
docs/source/_static/logo_hi.gif
docs/source/_static/repoze.css
repoze/__init__.py
repoze.what.egg-info/PKG-INFO
repoze.what.egg-info/SOURCES.txt
repoze.what.egg-info/dependency_links.txt
repoze.what.egg-info/entry_points.txt
repoze.what.egg-info/namespace_packages.txt
repoze.what.egg-info/not-zip-safe
repoze.what.egg-info/requires.txt
repoze.what.egg-info/top_level.txt
repoze/what/__init__.py
repoze/what/authorize.py
repoze/what/middleware.py
repoze/what/predicates.py
repoze/what/release.py
repoze/what/adapters/__init__.py
repoze/what/adapters/testutil.py
repoze/what/plugins/__init__.py